setup.py
twik/__init__.py
twik/__main__.py
twik/run.py
twik/twik.py
twik/util.py
twik.egg-info/PKG-INFO
twik.egg-info/SOURCES.txt
twik.egg-info/dependency_links.txt
twik.egg-info/entry_points.txt
twik.egg-info/top_level.txt