Metadata-Version: 1.0
Name: twik
Version: 0.4
Summary: Twik is an application that makes it easier to generate secure and different passwords for each website.
Home-page: https://github.com/coxande/Twik
Author: Alexandre Possebom
Author-email: alexandrepossebom@gmail.com
License: GPLv3
Keywords: twik password hash
Platform: UNKNOWN
